siaskynet/__init__.py
siaskynet/_download.py
siaskynet/_encryption.py
siaskynet/_upload.py
siaskynet/test_utils.py
siaskynet/utils.py
tests/__init__.py
tests/test_integration_download.py
tests/test_integration_upload.py
siaskynet-2.4.0.dist-info/LICENSE
siaskynet-2.4.0.dist-info/LICENSE.txt
siaskynet-2.4.0.dist-info/METADATA
siaskynet-2.4.0.dist-info/WHEEL
siaskynet-2.4.0.dist-info/top_level.txt
siaskynet-2.4.0.dist-info/RECORD
