Metadata-Version: 2.1
Name: siaskynet
Version: 2.4.0
Summary: Skynet SDK
Home-page: https://github.com/SkynetLabs/python-skynet
Author: Peter-Jan Brone
Author-email: peterjan.brone@gmail.com
License: UNKNOWN
Platform: UNKNOWN
Classifier: Programming Language :: Python :: 3
Classifier: License :: OSI Approved :: MIT License
Classifier: Operating System :: OS Independent
Requires-Python: >=3.6
Requires-Dist: requests
Requires-Dist: responses
